{
  "doc_id": "QD419_QĐ-TTg",
  "title": "Quyết định số 419/QĐ-TTg Phê duyệt “Chiến lược phát triển bóng đá Việt Nam đến năm 2020, tầm nhìn đến năm 2030”",
  "number": "419/QĐ-TTg",
  "doc_type": "Decision",
  "issued_by": "THỦ TƯỚNG CHÍNH PHỦ",
  "issued_date": "2013-03-08",
  "effective_from": "2013-03-08",
  "status": "Còn hiệu lực",
  "source_url": "https://vbpl.vn/van-ban/chi-tiet/quyet-dinh-so-419-qd-ttg-phe-duyet-chien-luoc-phat-trien-bong-da-viet-nam-den-nam-2020-tam-nhin-den-nam-2030--86510"
}